decycle/__init__.py
decycle/decorators.py
decycle/finder.py
decycle/loader.py
decycle/proxy.py
decycle/recursion_preventer.py
decycle/utils.py
decycle-2.0.0.dist-info/LICENSE
decycle-2.0.0.dist-info/METADATA
decycle-2.0.0.dist-info/WHEEL
decycle-2.0.0.dist-info/RECORD
